setup.cfg
setup.py
webunit2/__init__.py
webunit2/framework.py
webunit2/response.py
webunit2/testcase.py
webunit2/utils.py
webunit2.egg-info/PKG-INFO
webunit2.egg-info/SOURCES.txt
webunit2.egg-info/dependency_links.txt
webunit2.egg-info/requires.txt
webunit2.egg-info/top_level.txt
webunit2.egg-info/zip-safe