Metadata-Version: 1.0
Name: webunit2
Version: 0.2.2
Summary: Eases the testing of web services.
Home-page: https://github.com/amcfague/webunit2
Author: Andrew McFague
Author-email: redmumba@gmail.com
License: GPL
Platform: UNKNOWN
Classifier: Development Status :: 2 - Pre-Alpha
Classifier: Intended Audience :: Developers
Classifier: Programming Language :: Python
Classifier: Topic :: Software Development :: Testing
